argx/__init__.py
argx/action.py
argx/formatter.py
argx/parser.py
argx/py.typed
argx/type_.py
argx/utils.py
argx-0.4.2.dist-info/METADATA
argx-0.4.2.dist-info/WHEEL
argx-0.4.2.dist-info/licenses/LICENSE
argx-0.4.2.dist-info/RECORD
