Metadata-Version: 2.4
Name: argx
Version: 0.4.2
Summary: Super-charged argparse for python
License: MIT
License-File: LICENSE
Author: pwwang
Author-email: pwwang@pwwang.com
Requires-Python: >=3.9,<4.0
Classifier: License :: OSI Approved :: MIT License
Classifier: Programming Language :: Python :: 3
Classifier: Programming Language :: Python :: 3.9
Classifier: Programming Language :: Python :: 3.10
Classifier: Programming Language :: Python :: 3.11
Classifier: Programming Language :: Python :: 3.12
Classifier: Programming Language :: Python :: 3.13
Classifier: Programming Language :: Python :: 3.14
Provides-Extra: anypath
Provides-Extra: panpath
Requires-Dist: panpath (>=0.4,<0.5) ; extra == "anypath" or extra == "panpath"
Requires-Dist: python-simpleconf (>=0.8,<0.9)
